krossApy/__init__.py
krossApy/api/__init__.py
krossApy/api/api.py
krossApy/api/custom_fields_handlers.py
krossApy/api/custom_filters_handlers.py
krossApy/api/custom_types_handlers.py
krossApy/data/Errors.py
krossApy/data/Fields.py
krossApy/data/Filters.py
krossApy/data/Reservation.py
krossApy/data/Reservations.py
krossApy/data/__init__.py
krossApy/scraper/__init__.py
krossApy/scraper/scraper.py
krossapy-0.1.4.dist-info/licenses/LICENSE
krossapy-0.1.4.dist-info/METADATA
krossapy-0.1.4.dist-info/WHEEL
krossapy-0.1.4.dist-info/top_level.txt
krossapy-0.1.4.dist-info/RECORD
