Metadata-Version: 2.4
Name: krossApy
Version: 0.1.4
Summary: Unofficial API for KrossBooking
License-File: LICENSE
Requires-Dist: requests
Requires-Dist: beautifulsoup4
Dynamic: description
Dynamic: description-content-type
Dynamic: license-file
Dynamic: requires-dist
Dynamic: summary
